agentskills/__init__.py
agentskills/cli.py
agentskills/models.py
agentskills/providers.py
agentskills/registry.py
askill-0.2.0.dist-info/METADATA
askill-0.2.0.dist-info/WHEEL
askill-0.2.0.dist-info/entry_points.txt
askill-0.2.0.dist-info/licenses/LICENSE
askill-0.2.0.dist-info/RECORD
