Metadata-Version: 2.4
Name: askill
Version: 0.2.0
Summary: CLI for browsing and installing skills from anthropics/skills
Project-URL: Homepage, https://github.com/akshayaggarwal99/agentskills
Project-URL: Repository, https://github.com/akshayaggarwal99/agentskills
Project-URL: Issues, https://github.com/akshayaggarwal99/agentskills/issues
Author: Akshay Aggarwal
License-Expression: MIT
License-File: LICENSE
Keywords: agents,ai,anthropic,claude,mcp,skills
Classifier: Development Status :: 4 - Beta
Classifier: Environment :: Console
Classifier: Intended Audience :: Developers
Classifier: License :: OSI Approved :: MIT License
Classifier: Programming Language :: Python :: 3
Classifier: Programming Language :: Python :: 3.10
Classifier: Programming Language :: Python :: 3.11
Classifier: Programming Language :: Python :: 3.12
Classifier: Topic :: Software Development :: Libraries
Requires-Python: >=3.10
Requires-Dist: pyyaml>=6.0
Requires-Dist: rich>=13.0.0
Requires-Dist: typer>=0.9.0
